memory/__init__.py
memory/convert.py
memory/factory.py
memory/receiver.py
memory/sender.py
py_sharedmemory-2.0.1.dist-info/licenses/LICENSE
py_sharedmemory-2.0.1.dist-info/METADATA
py_sharedmemory-2.0.1.dist-info/WHEEL
py_sharedmemory-2.0.1.dist-info/top_level.txt
py_sharedmemory-2.0.1.dist-info/RECORD
