Metadata-Version: 2.4
Name: py-sharedmemory
Version: 2.0.1
Summary: Optimized Python IPC: Uses shared memory to bypass multiprocessing queue I/O bottlenecks, ideal for large data (1MB+) in scientific computing, RL, etc. Reduces system load and improves latency consistency
Author: Tobias Würth
License-Expression: MIT
Project-URL: Repository, https://github.com/tobiaswuerth/python_shared_memory_queue
Project-URL: Bug Tracker, https://github.com/tobiaswuerth/python_shared_memory_queue/issues
Keywords: python,performance,queue,multiprocessing,numpy,zero-copy,data-transfer,low-latency,inter-process-communication,shared-memory,high-throughput,parallel-processing,large-data,memoryview
Classifier: Programming Language :: Python :: 3
Classifier: Operating System :: OS Independent
Requires-Python: >=3.9
License-File: LICENSE
Dynamic: license-file
